mongolight/__init__.py
mongolight/base.py
mongolight/compiler.py
mongolight/creation.py
mongolight/exceptions.py
mongolight/features.py
mongolight/fields.py
mongolight/introspection.py
mongolight/operations.py
mongolight/schema.py
mongolight/utils.py
test/__init__.py
test/test_mongolight.py
django_mongolight-0.1.22.dist-info/LICENSE
django_mongolight-0.1.22.dist-info/METADATA
django_mongolight-0.1.22.dist-info/WHEEL
django_mongolight-0.1.22.dist-info/top_level.txt
django_mongolight-0.1.22.dist-info/RECORD
