Metadata-Version: 2.1
Name: django-mongolight
Version: 0.1.22
Summary: A lightweight library for integrating Django with MongoDB.
Home-page: https://github.com/bryancitu/django-mongolight
Author: Bryan Jesus Ramon Avila
Author-email: bryanjesus.ra@gmail.com
License: UNKNOWN
Platform: UNKNOWN
Classifier: Programming Language :: Python :: 3
Classifier: License :: OSI Approved :: MIT License
Classifier: Operating System :: OS Independent
Requires-Python: >=3.8
Requires-Dist: Django>=4.0
Requires-Dist: pymongo>=4.0
